Workbook

Sheet Instructions
A1: Coffee Capital System
A3: How to use
A4: 1. Go to the Unit Costs sheet.
A5: 2. Enter each ingredient's Purchase Qty and Purchase Cost in the yellow cells.
A6: 3. Review Recipe Summary for Capital Per Cup, Gross Profit, Profit Margin, and Capital % of Price.
A7: 4. If you change a recipe quantity, update the Recipe Usage sheet. The Cost Breakdown and Recipe Summary formulas will recalculate.
A8: 5. Use the Missing Cost Inputs and Status columns to see whether a recipe has all required cost data.
A11: Important assumptions
A12: Selling prices are entered exactly as provided.
A13: Quantities are counted only when the ingredient appears in the provided recipe list.
A14: Iced recipes use the Cup and Lid cost inputs; hot recipes use the separate Hot Cup and Hot Lid cost inputs.
A15: Hot coffee base data mentioned Straw, but hot recipes did not list Straw; hot recipe straw quantity is set to 0. Change Recipe Usage if you include a straw or stirrer.
... A19: Formula color guide
A20: Yellow | B20: Input cells: enter purchase quantity and cost.
A21: Green | B21: Formula cells: calculated automatically.
A22: Blue | B22: Table headers.
A23: Orange | B23: Notes and assumptions.

Sheet Unit Costs
A1: Ingredient | B1: Measurement Unit | C1: Purchase Qty | D1: Purchase Cost | E1: Cost Per Unit | F1: Notes
A2: Coffee | B2: g | E2: =IF(OR(C2="",D2=""),"",D2/C2) | F2: Enter coffee bag total grams and purchase cost.
A3: Milk | B3: ml | E3: =IF(OR(C3="",D3=""),"",D3/C3) | F3: Enter carton/bottle total ml and purchase cost.
A4: Cup | B4: pc | E4: =IF(OR(C4="",D4=""),"",D4/C4) | F4: Enter number of iced/cold cups per pack and pack cost.
A5: Lid | B5: pc | E5: =IF(OR(C5="",D5=""),"",D5/C5) | F5: Enter number of iced/cold lids per pack and pack cost.
A6: Hot Cup | B6: pc | E6: =IF(OR(C6="",D6=""),"",D6/C6) | F6: Enter number of hot cups per pack and pack cost.
A7: Hot Lid | B7: pc | E7: =IF(OR(C7="",D7=""),"",D7/C7) | F7: Enter number of hot lids per pack and pack cost.
A8: Ice | B8: g | E8: =IF(OR(C8="",D8=""),"",D8/C8) | F8: Enter total grams bought/produced and cost.
A9: Straw | B9: pc | E9: =IF(OR(C9="",D9=""),"",D9/C9) | F9: Enter number of straws per pack and pack cost.
A10: Water | B10: ml | E10: =IF(OR(C10="",D10=""),"",D10/C10) | F10: Enter total ml and cost if you want to include water.
A11: Condensed milk | B11: g | E11: =IF(OR(C11="",D11=""),"",D11/C11) | F11: Enter can/container total grams and cost.
A12: Ube powder | B12: g | E12: =IF(OR(C12="",D12=""),"",D12/C12) | F12: Enter pouch/container total grams and cost.
A13: Caramel Syrup | B13: g | E13: =IF(OR(C13="",D13=""),"",D13/C13) | F13: Enter bottle total grams and cost.
A14: Chocolate Syrup | B14: g | E14: =IF(OR(C14="",D14=""),"",D14/C14) | F14: Enter bottle total grams and cost.

Sheet Recipe Usage
A1: Type | B1: Recipe | C1: Selling Price | D1: Coffee (g) | E1: Milk (ml) | F1: Water (ml) | G1: Ice (g) | H1: Condensed milk (g) | I1: Ube powder (g) | J1: Caramel Syrup (g) | K1: Chocolate Syrup (g) | L1: Cup (pc) | M1: Lid (pc) | N1: Hot Cup (pc) | O1: Hot Lid (pc) | P1: Straw (pc)
A2: Iced | B2: Spanish latte | C2: 105 | D2: 18 | E2: 150 | F2: 0 | G2: 100 | H2: 30 | I2: 0 | J2: 0 | K2: 0 | L2: 1 | M2: 1 | N2: 0 | O2: 0 | P2: 1
A3: Iced | B3: Americano | C3: 70 | D3: 18 | E3: 0 | F3: 150 | G3: 100 | H3: 0 | I3: 0 | J3: 0 | K3: 0 | L3: 1 | M3: 1 | N3: 0 | O3: 0 | P3: 1
A4: Iced | B4: Latte | C4: 90 | D4: 18 | E4: 150 | F4: 0 | G4: 100 | H4: 0 | I4: 0 | J4: 0 | K4: 0 | L4: 1 | M4: 1 | N4: 0 | O4: 0 | P4: 1
A5: Iced | B5: Ube Latte | C5: 110 | D5: 18 | E5: 150 | F5: 0 | G5: 100 | H5: 30 | I5: 8 | J5: 0 | K5: 0 | L5: 1 | M5: 1 | N5: 0 | O5: 0 | P5: 1
A6: Iced | B6: Mocha Latte | C6: 110 | D6: 18 | E6: 150 | F6: 0 | G6: 100 | H6: 30 | I6: 0 | J6: 0 | K6: 35 | L6: 1 | M6: 1 | N6: 0 | O6: 0 | P6: 1
A7: Iced | B7: Caramel Macchiato | C7: 110 | D7: 18 | E7: 150 | F7: 0 | G7: 100 | H7: 30 | I7: 0 | J7: 35 | K7: 0 | L7: 1 | M7: 1 | N7: 0 | O7: 0 | P7: 1
A8: Iced | B8: Kape Sua Da | C8: 105 | D8: 18 | E8: 0 | F8: 150 | G8: 100 | H8: 30 | I8: 0 | J8: 0 | K8: 0 | L8: 1 | M8: 1 | N8: 0 | O8: 0 | P8: 1
A9: Hot | B9: Spanish latte | C9: 105 | D9: 18 | E9: 200 | F9: 0 | G9: 0 | H9: 30 | I9: 0 | J9: 0 | K9: 0 | L9: 0 | M9: 0 | N9: 1 | O9: 1 | P9: 0
A10: Hot | B10: Americano | C10: 70 | D10: 18 | E10: 0 | F10: 200 | G10: 0 | H10: 0 | I10: 0 | J10: 0 | K10: 0 | L10: 0 | M10: 0 | N10: 1 | O10: 1 | P10: 0
A11: Hot | B11: Latte | C11: 90 | D11: 18 | E11: 200 | F11: 0 | G11: 0 | H11: 0 | I11: 0 | J11: 0 | K11: 0 | L11: 0 | M11: 0 | N11: 1 | O11: 1 | P11: 0
A12: Hot | B12: Ube Latte | C12: 110 | D12: 18 | E12: 200 | F12: 0 | G12: 0 | H12: 30 | I12: 8 | J12: 0 | K12: 0 | L12: 0 | M12: 0 | N12: 1 | O12: 1 | P12: 0
A13: Hot | B13: Mocha Latte | C13: 110 | D13: 18 | E13: 200 | F13: 0 | G13: 0 | H13: 30 | I13: 0 | J13: 0 | K13: 35 | L13: 0 | M13: 0 | N13: 1 | O13: 1 | P13: 0
A14: Hot | B14: Caramel Macchiato | C14: 110 | D14: 18 | E14: 200 | F14: 0 | G14: 0 | H14: 30 | I14: 0 | J14: 35 | K14: 0 | L14: 0 | M14: 0 | N14: 1 | O14: 1 | P14: 0

Sheet Cost Breakdown
A1: Type | B1: Recipe | C1: Selling Price | D1: Ingredient | E1: Quantity | F1: Unit | G1: Cost Per Unit | H1: Ingredient Cost
A2: Iced | B2: Spanish latte | C2: 105 | D2: Coffee | E2: 18 | F2: g | G2: =IFERROR(VLOOKUP(D2,'Unit Costs'!$A$2:$E$14,5,FALSE),"") | H2: =IF(G2="","",E2*G2)
A3: Iced | B3: Spanish latte | C3: 105 | D3: Milk | E3: 150 | F3: ml | G3: =IFERROR(VLOOKUP(D3,'Unit Costs'!$A$2:$E$14,5,FALSE),"") | H3: =IF(G3="","",E3*G3)
A4: Iced | B4: Spanish latte | C4: 105 | D4: Ice | E4: 100 | F4: g | G4: =IFERROR(VLOOKUP(D4,'Unit Costs'!$A$2:$E$14,5,FALSE),"") | H4: =IF(G4="","",E4*G4)
A5: Iced | B5: Spanish latte | C5: 105 | D5: Condensed milk | E5: 30 | F5: g | G5: =IFERROR(VLOOKUP(D5,'Unit Costs'!$A$2:$E$14,5,FALSE),"") | H5: =IF(G5="","",E5*G5)
A6: Iced | B6: Spanish latte | C6: 105 | D6: Cup | E6: 1 | F6: pc | G6: =IFERROR(VLOOKUP(D6,'Unit Costs'!$A$2:$E$14,5,FALSE),"") | H6: =IF(G6="","",E6*G6)
A7: Iced | B7: Spanish latte | C7: 105 | D7: Lid | E7: 1 | F7: pc | G7: =IFERROR(VLOOKUP(D7,'Unit Costs'!$A$2:$E$14,5,FALSE),"") | H7: =IF(G7="","",E7*G7)
A8: Iced | B8: Spanish latte | C8: 105 | D8: Straw | E8: 1 | F8: pc | G8: =IFERROR(VLOOKUP(D8,'Unit Costs'!$A$2:$E$14,5,FALSE),"") | H8: =IF(G8="","",E8*G8)
A9: Iced | B9: Americano | C9: 70 | D9: Coffee | E9: 18 | F9: g | G9: =IFERROR(VLOOKUP(D9,'Unit Costs'!$A$2:$E$14,5,FALSE),"") | H9: =IF(G9="","",E9*G9)
A10: Iced | B10: Americano | C10: 70 | D10: Water | E10: 150 | F10: ml | G10: =IFERROR(VLOOKUP(D10,'Unit Costs'!$A$2:$E$14,5,FALSE),"") | H10: =IF(G10="","",E10*G10)
A11: Iced | B11: Americano | C11: 70 | D11: Ice | E11: 100 | F11: g | G11: =IFERROR(VLOOKUP(D11,'Unit Costs'!$A$2:$E$14,5,FALSE),"") | H11: =IF(G11="","",E11*G11)
A12: Iced | B12: Americano | C12: 70 | D12: Cup | E12: 1 | F12: pc | G12: =IFERROR(VLOOKUP(D12,'Unit Costs'!$A$2:$E$14,5,FALSE),"") | H12: =IF(G12="","",E12*G12)
A13: Iced | B13: Americano | C13: 70 | D13: Lid | E13: 1 | F13: pc | G13: =IFERROR(VLOOKUP(D13,'Unit Costs'!$A$2:$E$14,5,FALSE),"") | H13: =IF(G13="","",E13*G13)
... A82: Hot | B82: Caramel Macchiato | C82: 110 | D82: Hot Lid | E82: 1 | F82: pc | G82: =IFERROR(VLOOKUP(D82,'Unit Costs'!$A$2:$E$14,5,FALSE),"") | H82: =IF(G82="","",E82*G82)

Sheet Recipe Summary
A1: Type | B1: Recipe | C1: Selling Price | D1: Capital Per Cup | E1: Gross Profit Per Cup | F1: Profit Margin | G1: Capital % of Price | H1: Missing Cost Inputs | I1: Status
A2: Iced | B2: Spanish latte | C2: 105 | D2: =IF(COUNTIFS('Cost Breakdown'!$A:$A,A2,'Cost Breakdown'!$B:$B,B2,'Cost Breakdown'!$G:$G,"")>0,"",SUMIFS('Cost Breakdown'!$H:$H,'Cost Breakdown'!$A:$A,A2,'Cost Breakdown'!$B:$B,B2)) | E2: =IF(D2="","",C2-D2) | F2: =IF(D2="","",E2/C2) | G2: =IF(D2="","",D2/C2) | H2: =COUNTIFS('Cost Breakdown'!$A:$A,A2,'Cost Breakdown'!$B:$B,B2,'Cost Breakdown'!$G:$G,"") | I2: =IF(H2=0,"Complete","Enter unit costs")
A3: Iced | B3: Americano | C3: 70 | D3: =IF(COUNTIFS('Cost Breakdown'!$A:$A,A3,'Cost Breakdown'!$B:$B,B3,'Cost Breakdown'!$G:$G,"")>0,"",SUMIFS('Cost Breakdown'!$H:$H,'Cost Breakdown'!$A:$A,A3,'Cost Breakdown'!$B:$B,B3)) | E3: =IF(D3="","",C3-D3) | F3: =IF(D3="","",E3/C3) | G3: =IF(D3="","",D3/C3) | H3: =COUNTIFS('Cost Breakdown'!$A:$A,A3,'Cost Breakdown'!$B:$B,B3,'Cost Breakdown'!$G:$G,"") | I3: =IF(H3=0,"Complete","Enter unit costs")
A4: Iced | B4: Latte | C4: 90 | D4: =IF(COUNTIFS('Cost Breakdown'!$A:$A,A4,'Cost Breakdown'!$B:$B,B4,'Cost Breakdown'!$G:$G,"")>0,"",SUMIFS('Cost Breakdown'!$H:$H,'Cost Breakdown'!$A:$A,A4,'Cost Breakdown'!$B:$B,B4)) | E4: =IF(D4="","",C4-D4) | F4: =IF(D4="","",E4/C4) | G4: =IF(D4="","",D4/C4) | H4: =COUNTIFS('Cost Breakdown'!$A:$A,A4,'Cost Breakdown'!$B:$B,B4,'Cost Breakdown'!$G:$G,"") | I4: =IF(H4=0,"Complete","Enter unit costs")
A5: Iced | B5: Ube Latte | C5: 110 | D5: =IF(COUNTIFS('Cost Breakdown'!$A:$A,A5,'Cost Breakdown'!$B:$B,B5,'Cost Breakdown'!$G:$G,"")>0,"",SUMIFS('Cost Breakdown'!$H:$H,'Cost Breakdown'!$A:$A,A5,'Cost Breakdown'!$B:$B,B5)) | E5: =IF(D5="","",C5-D5) | F5: =IF(D5="","",E5/C5) | G5: =IF(D5="","",D5/C5) | H5: =COUNTIFS('Cost Breakdown'!$A:$A,A5,'Cost Breakdown'!$B:$B,B5,'Cost Breakdown'!$G:$G,"") | I5: =IF(H5=0,"Complete","Enter unit costs")
A6: Iced | B6: Mocha Latte | C6: 110 | D6: =IF(COUNTIFS('Cost Breakdown'!$A:$A,A6,'Cost Breakdown'!$B:$B,B6,'Cost Breakdown'!$G:$G,"")>0,"",SUMIFS('Cost Breakdown'!$H:$H,'Cost Breakdown'!$A:$A,A6,'Cost Breakdown'!$B:$B,B6)) | E6: =IF(D6="","",C6-D6) | F6: =IF(D6="","",E6/C6) | G6: =IF(D6="","",D6/C6) | H6: =COUNTIFS('Cost Breakdown'!$A:$A,A6,'Cost Breakdown'!$B:$B,B6,'Cost Breakdown'!$G:$G,"") | I6: =IF(H6=0,"Complete","Enter unit costs")
A7: Iced | B7: Caramel Macchiato | C7: 110 | D7: =IF(COUNTIFS('Cost Breakdown'!$A:$A,A7,'Cost Breakdown'!$B:$B,B7,'Cost Breakdown'!$G:$G,"")>0,"",SUMIFS('Cost Breakdown'!$H:$H,'Cost Breakdown'!$A:$A,A7,'Cost Breakdown'!$B:$B,B7)) | E7: =IF(D7="","",C7-D7) | F7: =IF(D7="","",E7/C7) | G7: =IF(D7="","",D7/C7) | H7: =COUNTIFS('Cost Breakdown'!$A:$A,A7,'Cost Breakdown'!$B:$B,B7,'Cost Breakdown'!$G:$G,"") | I7: =IF(H7=0,"Complete","Enter unit costs")
A8: Iced | B8: Kape Sua Da | C8: 105 | D8: =IF(COUNTIFS('Cost Breakdown'!$A:$A,A8,'Cost Breakdown'!$B:$B,B8,'Cost Breakdown'!$G:$G,"")>0,"",SUMIFS('Cost Breakdown'!$H:$H,'Cost Breakdown'!$A:$A,A8,'Cost Breakdown'!$B:$B,B8)) | E8: =IF(D8="","",C8-D8) | F8: =IF(D8="","",E8/C8) | G8: =IF(D8="","",D8/C8) | H8: =COUNTIFS('Cost Breakdown'!$A:$A,A8,'Cost Breakdown'!$B:$B,B8,'Cost Breakdown'!$G:$G,"") | I8: =IF(H8=0,"Complete","Enter unit costs")
A9: Hot | B9: Spanish latte | C9: 105 | D9: =IF(COUNTIFS('Cost Breakdown'!$A:$A,A9,'Cost Breakdown'!$B:$B,B9,'Cost Breakdown'!$G:$G,"")>0,"",SUMIFS('Cost Breakdown'!$H:$H,'Cost Breakdown'!$A:$A,A9,'Cost Breakdown'!$B:$B,B9)) | E9: =IF(D9="","",C9-D9) | F9: =IF(D9="","",E9/C9) | G9: =IF(D9="","",D9/C9) | H9: =COUNTIFS('Cost Breakdown'!$A:$A,A9,'Cost Breakdown'!$B:$B,B9,'Cost Breakdown'!$G:$G,"") | I9: =IF(H9=0,"Complete","Enter unit costs")
A10: Hot | B10: Americano | C10: 70 | D10: =IF(COUNTIFS('Cost Breakdown'!$A:$A,A10,'Cost Breakdown'!$B:$B,B10,'Cost Breakdown'!$G:$G,"")>0,"",SUMIFS('Cost Breakdown'!$H:$H,'Cost Breakdown'!$A:$A,A10,'Cost Breakdown'!$B:$B,B10)) | E10: =IF(D10="","",C10-D10) | F10: =IF(D10="","",E10/C10) | G10: =IF(D10="","",D10/C10) | H10: =COUNTIFS('Cost Breakdown'!$A:$A,A10,'Cost Breakdown'!$B:$B,B10,'Cost Breakdown'!$G:$G,"") | I10: =IF(H10=0,"Complete","Enter unit costs")
A11: Hot | B11: Latte | C11: 90 | D11: =IF(COUNTIFS('Cost Breakdown'!$A:$A,A11,'Cost Breakdown'!$B:$B,B11,'Cost Breakdown'!$G:$G,"")>0,"",SUMIFS('Cost Breakdown'!$H:$H,'Cost Breakdown'!$A:$A,A11,'Cost Breakdown'!$B:$B,B11)) | E11: =IF(D11="","",C11-D11) | F11: =IF(D11="","",E11/C11) | G11: =IF(D11="","",D11/C11) | H11: =COUNTIFS('Cost Breakdown'!$A:$A,A11,'Cost Breakdown'!$B:$B,B11,'Cost Breakdown'!$G:$G,"") | I11: =IF(H11=0,"Complete","Enter unit costs")
A12: Hot | B12: Ube Latte | C12: 110 | D12: =IF(COUNTIFS('Cost Breakdown'!$A:$A,A12,'Cost Breakdown'!$B:$B,B12,'Cost Breakdown'!$G:$G,"")>0,"",SUMIFS('Cost Breakdown'!$H:$H,'Cost Breakdown'!$A:$A,A12,'Cost Breakdown'!$B:$B,B12)) | E12: =IF(D12="","",C12-D12) | F12: =IF(D12="","",E12/C12) | G12: =IF(D12="","",D12/C12) | H12: =COUNTIFS('Cost Breakdown'!$A:$A,A12,'Cost Breakdown'!$B:$B,B12,'Cost Breakdown'!$G:$G,"") | I12: =IF(H12=0,"Complete","Enter unit costs")
A13: Hot | B13: Mocha Latte | C13: 110 | D13: =IF(COUNTIFS('Cost Breakdown'!$A:$A,A13,'Cost Breakdown'!$B:$B,B13,'Cost Breakdown'!$G:$G,"")>0,"",SUMIFS('Cost Breakdown'!$H:$H,'Cost Breakdown'!$A:$A,A13,'Cost Breakdown'!$B:$B,B13)) | E13: =IF(D13="","",C13-D13) | F13: =IF(D13="","",E13/C13) | G13: =IF(D13="","",D13/C13) | H13: =COUNTIFS('Cost Breakdown'!$A:$A,A13,'Cost Breakdown'!$B:$B,B13,'Cost Breakdown'!$G:$G,"") | I13: =IF(H13=0,"Complete","Enter unit costs")
A14: Hot | B14: Caramel Macchiato | C14: 110 | D14: =IF(COUNTIFS('Cost Breakdown'!$A:$A,A14,'Cost Breakdown'!$B:$B,B14,'Cost Breakdown'!$G:$G,"")>0,"",SUMIFS('Cost Breakdown'!$H:$H,'Cost Breakdown'!$A:$A,A14,'Cost Breakdown'!$B:$B,B14)) | E14: =IF(D14="","",C14-D14) | F14: =IF(D14="","",E14/C14) | G14: =IF(D14="","",D14/C14) | H14: =COUNTIFS('Cost Breakdown'!$A:$A,A14,'Cost Breakdown'!$B:$B,B14,'Cost Breakdown'!$G:$G,"") | I14: =IF(H14=0,"Complete","Enter unit costs")
