Workbook
Name UnitList: 'Units'!$A$2:$A$13
Name ItemIDList: 'Items'!$A$2:$A$201
Name ProductIDList: 'Products'!$A$2:$A$201

Sheet Instructions
A1: General Product Costing System
A3: How the system works
A4: 1. Update Units if you need more units or conversion factors.
A5: 2. Add or update ingredients, packaging, materials, or supplies in Items.
A6: 3. Add products and selling prices in Products.
A7: 4. Add each product's ingredients/materials in Recipe BOM.
A8: 5. Product Summary automatically calculates capital, gross profit, margin, and issues.
A11: Important
A12: Item costs are entered once in Items. Any recipe using that item updates when the item purchase cost changes.
A13: Product selling prices are entered once in Products. Product Summary updates when the price changes.
A14: This workbook starts empty, so you can build a new list of items, products, and recipes from scratch.
A15: Recipe units can differ from purchase units if both convert to the item's base unit. Example: buy flour by kg, use flour by g.
... A19: Color guide
A20: Yellow | B20: Input cells you edit.
A21: Green | B21: Formula cells that calculate automatically.
A22: Orange | B22: Notes and guidance.
A23: Blue | B23: Table headers.

Sheet Units
A1: Unit | B1: Unit Type | C1: Base Unit | D1: Factor to Base Unit | E1: Notes
A2: g | B2: Weight | C2: g | D2: 1 | E2: 1 g = 1 g
A3: kg | B3: Weight | C3: g | D3: 1000 | E3: 1 kg = 1000 g
A4: mg | B4: Weight | C4: g | D4: 0.001 | E4: 1 mg = 0.001 g
A5: oz | B5: Weight | C5: g | D5: 28.3495 | E5: 1 oz = 28.3495 g
A6: lb | B6: Weight | C6: g | D6: 453.592 | E6: 1 lb = 453.592 g
A7: ml | B7: Volume | C7: ml | D7: 1 | E7: 1 ml = 1 ml
A8: L | B8: Volume | C8: ml | D8: 1000 | E8: 1 L = 1000 ml
A9: fl oz | B9: Volume | C9: ml | D9: 29.5735 | E9: 1 fl oz = 29.5735 ml
A10: pc | B10: Count | C10: pc | D10: 1 | E10: 1 pc = 1 pc
A11: pcs | B11: Count | C11: pc | D11: 1 | E11: 1 pcs = 1 pc
A12: piece | B12: Count | C12: pc | D12: 1 | E12: 1 piece = 1 pc
A13: dozen | B13: Count | C13: pc | D13: 12 | E13: 1 dozen = 12 pc

Sheet Items
A1: Item ID | B1: Item Name | C1: Category | D1: Base Unit | E1: Purchase Qty | F1: Purchase Unit | G1: Purchase Cost | H1: Purchase Qty in Base Unit | I1: Waste % | J1: Cost Per Base Unit | K1: Status | L1: Notes
H2: =IF(OR(E2="",F2=""),"",IFERROR(E2*VLOOKUP(F2,'Units'!$A$2:$D$13,4,FALSE),"")) | J2: =IF(OR(G2="",H2=""),"",IFERROR(G2/(H2*(1-I2)),"")) | K2: =IF(AND(A2="",B2=""),"",IF(OR(A2="",B2="",D2="",E2="",F2="",G2=""),"Missing item data",IF(IFERROR(VLOOKUP(F2,'Units'!$A$2:$D$13,3,FALSE),"")<>D2,"Unit mismatch",IF(J2="","Check cost","OK"))))
H3: =IF(OR(E3="",F3=""),"",IFERROR(E3*VLOOKUP(F3,'Units'!$A$2:$D$13,4,FALSE),"")) | J3: =IF(OR(G3="",H3=""),"",IFERROR(G3/(H3*(1-I3)),"")) | K3: =IF(AND(A3="",B3=""),"",IF(OR(A3="",B3="",D3="",E3="",F3="",G3=""),"Missing item data",IF(IFERROR(VLOOKUP(F3,'Units'!$A$2:$D$13,3,FALSE),"")<>D3,"Unit mismatch",IF(J3="","Check cost","OK"))))
H4: =IF(OR(E4="",F4=""),"",IFERROR(E4*VLOOKUP(F4,'Units'!$A$2:$D$13,4,FALSE),"")) | J4: =IF(OR(G4="",H4=""),"",IFERROR(G4/(H4*(1-I4)),"")) | K4: =IF(AND(A4="",B4=""),"",IF(OR(A4="",B4="",D4="",E4="",F4="",G4=""),"Missing item data",IF(IFERROR(VLOOKUP(F4,'Units'!$A$2:$D$13,3,FALSE),"")<>D4,"Unit mismatch",IF(J4="","Check cost","OK"))))
H5: =IF(OR(E5="",F5=""),"",IFERROR(E5*VLOOKUP(F5,'Units'!$A$2:$D$13,4,FALSE),"")) | J5: =IF(OR(G5="",H5=""),"",IFERROR(G5/(H5*(1-I5)),"")) | K5: =IF(AND(A5="",B5=""),"",IF(OR(A5="",B5="",D5="",E5="",F5="",G5=""),"Missing item data",IF(IFERROR(VLOOKUP(F5,'Units'!$A$2:$D$13,3,FALSE),"")<>D5,"Unit mismatch",IF(J5="","Check cost","OK"))))
H6: =IF(OR(E6="",F6=""),"",IFERROR(E6*VLOOKUP(F6,'Units'!$A$2:$D$13,4,FALSE),"")) | J6: =IF(OR(G6="",H6=""),"",IFERROR(G6/(H6*(1-I6)),"")) | K6: =IF(AND(A6="",B6=""),"",IF(OR(A6="",B6="",D6="",E6="",F6="",G6=""),"Missing item data",IF(IFERROR(VLOOKUP(F6,'Units'!$A$2:$D$13,3,FALSE),"")<>D6,"Unit mismatch",IF(J6="","Check cost","OK"))))
H7: =IF(OR(E7="",F7=""),"",IFERROR(E7*VLOOKUP(F7,'Units'!$A$2:$D$13,4,FALSE),"")) | J7: =IF(OR(G7="",H7=""),"",IFERROR(G7/(H7*(1-I7)),"")) | K7: =IF(AND(A7="",B7=""),"",IF(OR(A7="",B7="",D7="",E7="",F7="",G7=""),"Missing item data",IF(IFERROR(VLOOKUP(F7,'Units'!$A$2:$D$13,3,FALSE),"")<>D7,"Unit mismatch",IF(J7="","Check cost","OK"))))
H8: =IF(OR(E8="",F8=""),"",IFERROR(E8*VLOOKUP(F8,'Units'!$A$2:$D$13,4,FALSE),"")) | J8: =IF(OR(G8="",H8=""),"",IFERROR(G8/(H8*(1-I8)),"")) | K8: =IF(AND(A8="",B8=""),"",IF(OR(A8="",B8="",D8="",E8="",F8="",G8=""),"Missing item data",IF(IFERROR(VLOOKUP(F8,'Units'!$A$2:$D$13,3,FALSE),"")<>D8,"Unit mismatch",IF(J8="","Check cost","OK"))))
H9: =IF(OR(E9="",F9=""),"",IFERROR(E9*VLOOKUP(F9,'Units'!$A$2:$D$13,4,FALSE),"")) | J9: =IF(OR(G9="",H9=""),"",IFERROR(G9/(H9*(1-I9)),"")) | K9: =IF(AND(A9="",B9=""),"",IF(OR(A9="",B9="",D9="",E9="",F9="",G9=""),"Missing item data",IF(IFERROR(VLOOKUP(F9,'Units'!$A$2:$D$13,3,FALSE),"")<>D9,"Unit mismatch",IF(J9="","Check cost","OK"))))
H10: =IF(OR(E10="",F10=""),"",IFERROR(E10*VLOOKUP(F10,'Units'!$A$2:$D$13,4,FALSE),"")) | J10: =IF(OR(G10="",H10=""),"",IFERROR(G10/(H10*(1-I10)),"")) | K10: =IF(AND(A10="",B10=""),"",IF(OR(A10="",B10="",D10="",E10="",F10="",G10=""),"Missing item data",IF(IFERROR(VLOOKUP(F10,'Units'!$A$2:$D$13,3,FALSE),"")<>D10,"Unit mismatch",IF(J10="","Check cost","OK"))))
H11: =IF(OR(E11="",F11=""),"",IFERROR(E11*VLOOKUP(F11,'Units'!$A$2:$D$13,4,FALSE),"")) | J11: =IF(OR(G11="",H11=""),"",IFERROR(G11/(H11*(1-I11)),"")) | K11: =IF(AND(A11="",B11=""),"",IF(OR(A11="",B11="",D11="",E11="",F11="",G11=""),"Missing item data",IF(IFERROR(VLOOKUP(F11,'Units'!$A$2:$D$13,3,FALSE),"")<>D11,"Unit mismatch",IF(J11="","Check cost","OK"))))
H12: =IF(OR(E12="",F12=""),"",IFERROR(E12*VLOOKUP(F12,'Units'!$A$2:$D$13,4,FALSE),"")) | J12: =IF(OR(G12="",H12=""),"",IFERROR(G12/(H12*(1-I12)),"")) | K12: =IF(AND(A12="",B12=""),"",IF(OR(A12="",B12="",D12="",E12="",F12="",G12=""),"Missing item data",IF(IFERROR(VLOOKUP(F12,'Units'!$A$2:$D$13,3,FALSE),"")<>D12,"Unit mismatch",IF(J12="","Check cost","OK"))))
H13: =IF(OR(E13="",F13=""),"",IFERROR(E13*VLOOKUP(F13,'Units'!$A$2:$D$13,4,FALSE),"")) | J13: =IF(OR(G13="",H13=""),"",IFERROR(G13/(H13*(1-I13)),"")) | K13: =IF(AND(A13="",B13=""),"",IF(OR(A13="",B13="",D13="",E13="",F13="",G13=""),"Missing item data",IF(IFERROR(VLOOKUP(F13,'Units'!$A$2:$D$13,3,FALSE),"")<>D13,"Unit mismatch",IF(J13="","Check cost","OK"))))
... H201: =IF(OR(E201="",F201=""),"",IFERROR(E201*VLOOKUP(F201,'Units'!$A$2:$D$13,4,FALSE),"")) | J201: =IF(OR(G201="",H201=""),"",IFERROR(G201/(H201*(1-I201)),"")) | K201: =IF(AND(A201="",B201=""),"",IF(OR(A201="",B201="",D201="",E201="",F201="",G201=""),"Missing item data",IF(IFERROR(VLOOKUP(F201,'Units'!$A$2:$D$13,3,FALSE),"")<>D201,"Unit mismatch",IF(J201="","Check cost","OK"))))

Sheet Products
A1: Product ID | B1: Product Name | C1: Category | D1: Selling Price | E1: Active? | F1: Notes

Sheet Recipe BOM
A1: Line ID | B1: Product ID | C1: Product Name | D1: Item ID | E1: Item Name | F1: Quantity | G1: Recipe Unit | H1: Qty in Item Base Unit | I1: Item Base Unit | J1: Cost Per Base Unit | K1: Line Cost | L1: Status | M1: Notes
A2: =IF(AND(B2="",D2=""),"",ROW()-1) | C2: =IF(B2="","",IFERROR(VLOOKUP(B2,'Products'!$A$2:$F$201,2,FALSE),"Product not found")) | E2: =IF(D2="","",IFERROR(VLOOKUP(D2,'Items'!$A$2:$L$201,2,FALSE),"Item not found")) | H2: =IF(OR(F2="",G2=""),"",IFERROR(F2*VLOOKUP(G2,'Units'!$A$2:$D$13,4,FALSE),"")) | I2: =IF(D2="","",IFERROR(VLOOKUP(D2,'Items'!$A$2:$L$201,4,FALSE),"")) | J2: =IF(D2="","",IFERROR(VLOOKUP(D2,'Items'!$A$2:$L$201,10,FALSE),"")) | K2: =IF(OR(H2="",J2=""),"",H2*J2) | L2: =IF(AND(B2="",D2=""),"",IF(B2="","Missing product",IF(D2="","Missing item",IF(C2="Product not found","Product not found",IF(E2="Item not found","Item not found",IF(OR(F2="",G2=""),"Missing quantity/unit",IF(IFERROR(VLOOKUP(G2,'Units'!$A$2:$D$13,3,FALSE),"")<>I2,"Unit mismatch",IF(J2="","Enter item cost","OK"))))))))
A3: =IF(AND(B3="",D3=""),"",ROW()-1) | C3: =IF(B3="","",IFERROR(VLOOKUP(B3,'Products'!$A$2:$F$201,2,FALSE),"Product not found")) | E3: =IF(D3="","",IFERROR(VLOOKUP(D3,'Items'!$A$2:$L$201,2,FALSE),"Item not found")) | H3: =IF(OR(F3="",G3=""),"",IFERROR(F3*VLOOKUP(G3,'Units'!$A$2:$D$13,4,FALSE),"")) | I3: =IF(D3="","",IFERROR(VLOOKUP(D3,'Items'!$A$2:$L$201,4,FALSE),"")) | J3: =IF(D3="","",IFERROR(VLOOKUP(D3,'Items'!$A$2:$L$201,10,FALSE),"")) | K3: =IF(OR(H3="",J3=""),"",H3*J3) | L3: =IF(AND(B3="",D3=""),"",IF(B3="","Missing product",IF(D3="","Missing item",IF(C3="Product not found","Product not found",IF(E3="Item not found","Item not found",IF(OR(F3="",G3=""),"Missing quantity/unit",IF(IFERROR(VLOOKUP(G3,'Units'!$A$2:$D$13,3,FALSE),"")<>I3,"Unit mismatch",IF(J3="","Enter item cost","OK"))))))))
A4: =IF(AND(B4="",D4=""),"",ROW()-1) | C4: =IF(B4="","",IFERROR(VLOOKUP(B4,'Products'!$A$2:$F$201,2,FALSE),"Product not found")) | E4: =IF(D4="","",IFERROR(VLOOKUP(D4,'Items'!$A$2:$L$201,2,FALSE),"Item not found")) | H4: =IF(OR(F4="",G4=""),"",IFERROR(F4*VLOOKUP(G4,'Units'!$A$2:$D$13,4,FALSE),"")) | I4: =IF(D4="","",IFERROR(VLOOKUP(D4,'Items'!$A$2:$L$201,4,FALSE),"")) | J4: =IF(D4="","",IFERROR(VLOOKUP(D4,'Items'!$A$2:$L$201,10,FALSE),"")) | K4: =IF(OR(H4="",J4=""),"",H4*J4) | L4: =IF(AND(B4="",D4=""),"",IF(B4="","Missing product",IF(D4="","Missing item",IF(C4="Product not found","Product not found",IF(E4="Item not found","Item not found",IF(OR(F4="",G4=""),"Missing quantity/unit",IF(IFERROR(VLOOKUP(G4,'Units'!$A$2:$D$13,3,FALSE),"")<>I4,"Unit mismatch",IF(J4="","Enter item cost","OK"))))))))
A5: =IF(AND(B5="",D5=""),"",ROW()-1) | C5: =IF(B5="","",IFERROR(VLOOKUP(B5,'Products'!$A$2:$F$201,2,FALSE),"Product not found")) | E5: =IF(D5="","",IFERROR(VLOOKUP(D5,'Items'!$A$2:$L$201,2,FALSE),"Item not found")) | H5: =IF(OR(F5="",G5=""),"",IFERROR(F5*VLOOKUP(G5,'Units'!$A$2:$D$13,4,FALSE),"")) | I5: =IF(D5="","",IFERROR(VLOOKUP(D5,'Items'!$A$2:$L$201,4,FALSE),"")) | J5: =IF(D5="","",IFERROR(VLOOKUP(D5,'Items'!$A$2:$L$201,10,FALSE),"")) | K5: =IF(OR(H5="",J5=""),"",H5*J5) | L5: =IF(AND(B5="",D5=""),"",IF(B5="","Missing product",IF(D5="","Missing item",IF(C5="Product not found","Product not found",IF(E5="Item not found","Item not found",IF(OR(F5="",G5=""),"Missing quantity/unit",IF(IFERROR(VLOOKUP(G5,'Units'!$A$2:$D$13,3,FALSE),"")<>I5,"Unit mismatch",IF(J5="","Enter item cost","OK"))))))))
A6: =IF(AND(B6="",D6=""),"",ROW()-1) | C6: =IF(B6="","",IFERROR(VLOOKUP(B6,'Products'!$A$2:$F$201,2,FALSE),"Product not found")) | E6: =IF(D6="","",IFERROR(VLOOKUP(D6,'Items'!$A$2:$L$201,2,FALSE),"Item not found")) | H6: =IF(OR(F6="",G6=""),"",IFERROR(F6*VLOOKUP(G6,'Units'!$A$2:$D$13,4,FALSE),"")) | I6: =IF(D6="","",IFERROR(VLOOKUP(D6,'Items'!$A$2:$L$201,4,FALSE),"")) | J6: =IF(D6="","",IFERROR(VLOOKUP(D6,'Items'!$A$2:$L$201,10,FALSE),"")) | K6: =IF(OR(H6="",J6=""),"",H6*J6) | L6: =IF(AND(B6="",D6=""),"",IF(B6="","Missing product",IF(D6="","Missing item",IF(C6="Product not found","Product not found",IF(E6="Item not found","Item not found",IF(OR(F6="",G6=""),"Missing quantity/unit",IF(IFERROR(VLOOKUP(G6,'Units'!$A$2:$D$13,3,FALSE),"")<>I6,"Unit mismatch",IF(J6="","Enter item cost","OK"))))))))
A7: =IF(AND(B7="",D7=""),"",ROW()-1) | C7: =IF(B7="","",IFERROR(VLOOKUP(B7,'Products'!$A$2:$F$201,2,FALSE),"Product not found")) | E7: =IF(D7="","",IFERROR(VLOOKUP(D7,'Items'!$A$2:$L$201,2,FALSE),"Item not found")) | H7: =IF(OR(F7="",G7=""),"",IFERROR(F7*VLOOKUP(G7,'Units'!$A$2:$D$13,4,FALSE),"")) | I7: =IF(D7="","",IFERROR(VLOOKUP(D7,'Items'!$A$2:$L$201,4,FALSE),"")) | J7: =IF(D7="","",IFERROR(VLOOKUP(D7,'Items'!$A$2:$L$201,10,FALSE),"")) | K7: =IF(OR(H7="",J7=""),"",H7*J7) | L7: =IF(AND(B7="",D7=""),"",IF(B7="","Missing product",IF(D7="","Missing item",IF(C7="Product not found","Product not found",IF(E7="Item not found","Item not found",IF(OR(F7="",G7=""),"Missing quantity/unit",IF(IFERROR(VLOOKUP(G7,'Units'!$A$2:$D$13,3,FALSE),"")<>I7,"Unit mismatch",IF(J7="","Enter item cost","OK"))))))))
A8: =IF(AND(B8="",D8=""),"",ROW()-1) | C8: =IF(B8="","",IFERROR(VLOOKUP(B8,'Products'!$A$2:$F$201,2,FALSE),"Product not found")) | E8: =IF(D8="","",IFERROR(VLOOKUP(D8,'Items'!$A$2:$L$201,2,FALSE),"Item not found")) | H8: =IF(OR(F8="",G8=""),"",IFERROR(F8*VLOOKUP(G8,'Units'!$A$2:$D$13,4,FALSE),"")) | I8: =IF(D8="","",IFERROR(VLOOKUP(D8,'Items'!$A$2:$L$201,4,FALSE),"")) | J8: =IF(D8="","",IFERROR(VLOOKUP(D8,'Items'!$A$2:$L$201,10,FALSE),"")) | K8: =IF(OR(H8="",J8=""),"",H8*J8) | L8: =IF(AND(B8="",D8=""),"",IF(B8="","Missing product",IF(D8="","Missing item",IF(C8="Product not found","Product not found",IF(E8="Item not found","Item not found",IF(OR(F8="",G8=""),"Missing quantity/unit",IF(IFERROR(VLOOKUP(G8,'Units'!$A$2:$D$13,3,FALSE),"")<>I8,"Unit mismatch",IF(J8="","Enter item cost","OK"))))))))
A9: =IF(AND(B9="",D9=""),"",ROW()-1) | C9: =IF(B9="","",IFERROR(VLOOKUP(B9,'Products'!$A$2:$F$201,2,FALSE),"Product not found")) | E9: =IF(D9="","",IFERROR(VLOOKUP(D9,'Items'!$A$2:$L$201,2,FALSE),"Item not found")) | H9: =IF(OR(F9="",G9=""),"",IFERROR(F9*VLOOKUP(G9,'Units'!$A$2:$D$13,4,FALSE),"")) | I9: =IF(D9="","",IFERROR(VLOOKUP(D9,'Items'!$A$2:$L$201,4,FALSE),"")) | J9: =IF(D9="","",IFERROR(VLOOKUP(D9,'Items'!$A$2:$L$201,10,FALSE),"")) | K9: =IF(OR(H9="",J9=""),"",H9*J9) | L9: =IF(AND(B9="",D9=""),"",IF(B9="","Missing product",IF(D9="","Missing item",IF(C9="Product not found","Product not found",IF(E9="Item not found","Item not found",IF(OR(F9="",G9=""),"Missing quantity/unit",IF(IFERROR(VLOOKUP(G9,'Units'!$A$2:$D$13,3,FALSE),"")<>I9,"Unit mismatch",IF(J9="","Enter item cost","OK"))))))))
A10: =IF(AND(B10="",D10=""),"",ROW()-1) | C10: =IF(B10="","",IFERROR(VLOOKUP(B10,'Products'!$A$2:$F$201,2,FALSE),"Product not found")) | E10: =IF(D10="","",IFERROR(VLOOKUP(D10,'Items'!$A$2:$L$201,2,FALSE),"Item not found")) | H10: =IF(OR(F10="",G10=""),"",IFERROR(F10*VLOOKUP(G10,'Units'!$A$2:$D$13,4,FALSE),"")) | I10: =IF(D10="","",IFERROR(VLOOKUP(D10,'Items'!$A$2:$L$201,4,FALSE),"")) | J10: =IF(D10="","",IFERROR(VLOOKUP(D10,'Items'!$A$2:$L$201,10,FALSE),"")) | K10: =IF(OR(H10="",J10=""),"",H10*J10) | L10: =IF(AND(B10="",D10=""),"",IF(B10="","Missing product",IF(D10="","Missing item",IF(C10="Product not found","Product not found",IF(E10="Item not found","Item not found",IF(OR(F10="",G10=""),"Missing quantity/unit",IF(IFERROR(VLOOKUP(G10,'Units'!$A$2:$D$13,3,FALSE),"")<>I10,"Unit mismatch",IF(J10="","Enter item cost","OK"))))))))
A11: =IF(AND(B11="",D11=""),"",ROW()-1) | C11: =IF(B11="","",IFERROR(VLOOKUP(B11,'Products'!$A$2:$F$201,2,FALSE),"Product not found")) | E11: =IF(D11="","",IFERROR(VLOOKUP(D11,'Items'!$A$2:$L$201,2,FALSE),"Item not found")) | H11: =IF(OR(F11="",G11=""),"",IFERROR(F11*VLOOKUP(G11,'Units'!$A$2:$D$13,4,FALSE),"")) | I11: =IF(D11="","",IFERROR(VLOOKUP(D11,'Items'!$A$2:$L$201,4,FALSE),"")) | J11: =IF(D11="","",IFERROR(VLOOKUP(D11,'Items'!$A$2:$L$201,10,FALSE),"")) | K11: =IF(OR(H11="",J11=""),"",H11*J11) | L11: =IF(AND(B11="",D11=""),"",IF(B11="","Missing product",IF(D11="","Missing item",IF(C11="Product not found","Product not found",IF(E11="Item not found","Item not found",IF(OR(F11="",G11=""),"Missing quantity/unit",IF(IFERROR(VLOOKUP(G11,'Units'!$A$2:$D$13,3,FALSE),"")<>I11,"Unit mismatch",IF(J11="","Enter item cost","OK"))))))))
A12: =IF(AND(B12="",D12=""),"",ROW()-1) | C12: =IF(B12="","",IFERROR(VLOOKUP(B12,'Products'!$A$2:$F$201,2,FALSE),"Product not found")) | E12: =IF(D12="","",IFERROR(VLOOKUP(D12,'Items'!$A$2:$L$201,2,FALSE),"Item not found")) | H12: =IF(OR(F12="",G12=""),"",IFERROR(F12*VLOOKUP(G12,'Units'!$A$2:$D$13,4,FALSE),"")) | I12: =IF(D12="","",IFERROR(VLOOKUP(D12,'Items'!$A$2:$L$201,4,FALSE),"")) | J12: =IF(D12="","",IFERROR(VLOOKUP(D12,'Items'!$A$2:$L$201,10,FALSE),"")) | K12: =IF(OR(H12="",J12=""),"",H12*J12) | L12: =IF(AND(B12="",D12=""),"",IF(B12="","Missing product",IF(D12="","Missing item",IF(C12="Product not found","Product not found",IF(E12="Item not found","Item not found",IF(OR(F12="",G12=""),"Missing quantity/unit",IF(IFERROR(VLOOKUP(G12,'Units'!$A$2:$D$13,3,FALSE),"")<>I12,"Unit mismatch",IF(J12="","Enter item cost","OK"))))))))
A13: =IF(AND(B13="",D13=""),"",ROW()-1) | C13: =IF(B13="","",IFERROR(VLOOKUP(B13,'Products'!$A$2:$F$201,2,FALSE),"Product not found")) | E13: =IF(D13="","",IFERROR(VLOOKUP(D13,'Items'!$A$2:$L$201,2,FALSE),"Item not found")) | H13: =IF(OR(F13="",G13=""),"",IFERROR(F13*VLOOKUP(G13,'Units'!$A$2:$D$13,4,FALSE),"")) | I13: =IF(D13="","",IFERROR(VLOOKUP(D13,'Items'!$A$2:$L$201,4,FALSE),"")) | J13: =IF(D13="","",IFERROR(VLOOKUP(D13,'Items'!$A$2:$L$201,10,FALSE),"")) | K13: =IF(OR(H13="",J13=""),"",H13*J13) | L13: =IF(AND(B13="",D13=""),"",IF(B13="","Missing product",IF(D13="","Missing item",IF(C13="Product not found","Product not found",IF(E13="Item not found","Item not found",IF(OR(F13="",G13=""),"Missing quantity/unit",IF(IFERROR(VLOOKUP(G13,'Units'!$A$2:$D$13,3,FALSE),"")<>I13,"Unit mismatch",IF(J13="","Enter item cost","OK"))))))))
... A1001: =IF(AND(B1001="",D1001=""),"",ROW()-1) | C1001: =IF(B1001="","",IFERROR(VLOOKUP(B1001,'Products'!$A$2:$F$201,2,FALSE),"Product not found")) | E1001: =IF(D1001="","",IFERROR(VLOOKUP(D1001,'Items'!$A$2:$L$201,2,FALSE),"Item not found")) | H1001: =IF(OR(F1001="",G1001=""),"",IFERROR(F1001*VLOOKUP(G1001,'Units'!$A$2:$D$13,4,FALSE),"")) | I1001: =IF(D1001="","",IFERROR(VLOOKUP(D1001,'Items'!$A$2:$L$201,4,FALSE),"")) | J1001: =IF(D1001="","",IFERROR(VLOOKUP(D1001,'Items'!$A$2:$L$201,10,FALSE),"")) | K1001: =IF(OR(H1001="",J1001=""),"",H1001*J1001) | L1001: =IF(AND(B1001="",D1001=""),"",IF(B1001="","Missing product",IF(D1001="","Missing item",IF(C1001="Product not found","Product not found",IF(E1001="Item not found","Item not found",IF(OR(F1001="",G1001=""),"Missing quantity/unit",IF(IFERROR(VLOOKUP(G1001,'Units'!$A$2:$D$13,3,FALSE),"")<>I1001,"Unit mismatch",IF(J1001="","Enter item cost","OK"))))))))

Sheet Product Summary
A1: Product ID | B1: Product Name | C1: Category | D1: Selling Price | E1: Capital / Total Cost | F1: Gross Profit | G1: Profit Margin | H1: Cost % of Price | I1: Recipe Lines | J1: Issues | K1: Status
A2: =IF(Products!A2="","",Products!A2) | B2: =IF(A2="","",Products!B2) | C2: =IF(A2="","",Products!C2) | D2: =IF(A2="","",Products!D2) | E2: =IF(A2="","",SUMIFS('Recipe BOM'!$K:$K,'Recipe BOM'!$B:$B,A2)) | F2: =IF(OR(A2="",D2="",E2=""),"",D2-E2) | G2: =IF(OR(A2="",D2="",E2=""),"",F2/D2) | H2: =IF(OR(A2="",D2="",E2=""),"",E2/D2) | I2: =IF(A2="","",COUNTIFS('Recipe BOM'!$B:$B,A2,'Recipe BOM'!$D:$D,"<>")) | J2: =IF(A2="","",COUNTIFS('Recipe BOM'!$B:$B,A2,'Recipe BOM'!$D:$D,"<>",'Recipe BOM'!$L:$L,"<>OK")) | K2: =IF(A2="","",IF(I2=0,"No recipe",IF(J2>0,"Check recipe/items",IF(D2="","Enter selling price","OK"))))
A3: =IF(Products!A3="","",Products!A3) | B3: =IF(A3="","",Products!B3) | C3: =IF(A3="","",Products!C3) | D3: =IF(A3="","",Products!D3) | E3: =IF(A3="","",SUMIFS('Recipe BOM'!$K:$K,'Recipe BOM'!$B:$B,A3)) | F3: =IF(OR(A3="",D3="",E3=""),"",D3-E3) | G3: =IF(OR(A3="",D3="",E3=""),"",F3/D3) | H3: =IF(OR(A3="",D3="",E3=""),"",E3/D3) | I3: =IF(A3="","",COUNTIFS('Recipe BOM'!$B:$B,A3,'Recipe BOM'!$D:$D,"<>")) | J3: =IF(A3="","",COUNTIFS('Recipe BOM'!$B:$B,A3,'Recipe BOM'!$D:$D,"<>",'Recipe BOM'!$L:$L,"<>OK")) | K3: =IF(A3="","",IF(I3=0,"No recipe",IF(J3>0,"Check recipe/items",IF(D3="","Enter selling price","OK"))))
A4: =IF(Products!A4="","",Products!A4) | B4: =IF(A4="","",Products!B4) | C4: =IF(A4="","",Products!C4) | D4: =IF(A4="","",Products!D4) | E4: =IF(A4="","",SUMIFS('Recipe BOM'!$K:$K,'Recipe BOM'!$B:$B,A4)) | F4: =IF(OR(A4="",D4="",E4=""),"",D4-E4) | G4: =IF(OR(A4="",D4="",E4=""),"",F4/D4) | H4: =IF(OR(A4="",D4="",E4=""),"",E4/D4) | I4: =IF(A4="","",COUNTIFS('Recipe BOM'!$B:$B,A4,'Recipe BOM'!$D:$D,"<>")) | J4: =IF(A4="","",COUNTIFS('Recipe BOM'!$B:$B,A4,'Recipe BOM'!$D:$D,"<>",'Recipe BOM'!$L:$L,"<>OK")) | K4: =IF(A4="","",IF(I4=0,"No recipe",IF(J4>0,"Check recipe/items",IF(D4="","Enter selling price","OK"))))
A5: =IF(Products!A5="","",Products!A5) | B5: =IF(A5="","",Products!B5) | C5: =IF(A5="","",Products!C5) | D5: =IF(A5="","",Products!D5) | E5: =IF(A5="","",SUMIFS('Recipe BOM'!$K:$K,'Recipe BOM'!$B:$B,A5)) | F5: =IF(OR(A5="",D5="",E5=""),"",D5-E5) | G5: =IF(OR(A5="",D5="",E5=""),"",F5/D5) | H5: =IF(OR(A5="",D5="",E5=""),"",E5/D5) | I5: =IF(A5="","",COUNTIFS('Recipe BOM'!$B:$B,A5,'Recipe BOM'!$D:$D,"<>")) | J5: =IF(A5="","",COUNTIFS('Recipe BOM'!$B:$B,A5,'Recipe BOM'!$D:$D,"<>",'Recipe BOM'!$L:$L,"<>OK")) | K5: =IF(A5="","",IF(I5=0,"No recipe",IF(J5>0,"Check recipe/items",IF(D5="","Enter selling price","OK"))))
A6: =IF(Products!A6="","",Products!A6) | B6: =IF(A6="","",Products!B6) | C6: =IF(A6="","",Products!C6) | D6: =IF(A6="","",Products!D6) | E6: =IF(A6="","",SUMIFS('Recipe BOM'!$K:$K,'Recipe BOM'!$B:$B,A6)) | F6: =IF(OR(A6="",D6="",E6=""),"",D6-E6) | G6: =IF(OR(A6="",D6="",E6=""),"",F6/D6) | H6: =IF(OR(A6="",D6="",E6=""),"",E6/D6) | I6: =IF(A6="","",COUNTIFS('Recipe BOM'!$B:$B,A6,'Recipe BOM'!$D:$D,"<>")) | J6: =IF(A6="","",COUNTIFS('Recipe BOM'!$B:$B,A6,'Recipe BOM'!$D:$D,"<>",'Recipe BOM'!$L:$L,"<>OK")) | K6: =IF(A6="","",IF(I6=0,"No recipe",IF(J6>0,"Check recipe/items",IF(D6="","Enter selling price","OK"))))
A7: =IF(Products!A7="","",Products!A7) | B7: =IF(A7="","",Products!B7) | C7: =IF(A7="","",Products!C7) | D7: =IF(A7="","",Products!D7) | E7: =IF(A7="","",SUMIFS('Recipe BOM'!$K:$K,'Recipe BOM'!$B:$B,A7)) | F7: =IF(OR(A7="",D7="",E7=""),"",D7-E7) | G7: =IF(OR(A7="",D7="",E7=""),"",F7/D7) | H7: =IF(OR(A7="",D7="",E7=""),"",E7/D7) | I7: =IF(A7="","",COUNTIFS('Recipe BOM'!$B:$B,A7,'Recipe BOM'!$D:$D,"<>")) | J7: =IF(A7="","",COUNTIFS('Recipe BOM'!$B:$B,A7,'Recipe BOM'!$D:$D,"<>",'Recipe BOM'!$L:$L,"<>OK")) | K7: =IF(A7="","",IF(I7=0,"No recipe",IF(J7>0,"Check recipe/items",IF(D7="","Enter selling price","OK"))))
A8: =IF(Products!A8="","",Products!A8) | B8: =IF(A8="","",Products!B8) | C8: =IF(A8="","",Products!C8) | D8: =IF(A8="","",Products!D8) | E8: =IF(A8="","",SUMIFS('Recipe BOM'!$K:$K,'Recipe BOM'!$B:$B,A8)) | F8: =IF(OR(A8="",D8="",E8=""),"",D8-E8) | G8: =IF(OR(A8="",D8="",E8=""),"",F8/D8) | H8: =IF(OR(A8="",D8="",E8=""),"",E8/D8) | I8: =IF(A8="","",COUNTIFS('Recipe BOM'!$B:$B,A8,'Recipe BOM'!$D:$D,"<>")) | J8: =IF(A8="","",COUNTIFS('Recipe BOM'!$B:$B,A8,'Recipe BOM'!$D:$D,"<>",'Recipe BOM'!$L:$L,"<>OK")) | K8: =IF(A8="","",IF(I8=0,"No recipe",IF(J8>0,"Check recipe/items",IF(D8="","Enter selling price","OK"))))
A9: =IF(Products!A9="","",Products!A9) | B9: =IF(A9="","",Products!B9) | C9: =IF(A9="","",Products!C9) | D9: =IF(A9="","",Products!D9) | E9: =IF(A9="","",SUMIFS('Recipe BOM'!$K:$K,'Recipe BOM'!$B:$B,A9)) | F9: =IF(OR(A9="",D9="",E9=""),"",D9-E9) | G9: =IF(OR(A9="",D9="",E9=""),"",F9/D9) | H9: =IF(OR(A9="",D9="",E9=""),"",E9/D9) | I9: =IF(A9="","",COUNTIFS('Recipe BOM'!$B:$B,A9,'Recipe BOM'!$D:$D,"<>")) | J9: =IF(A9="","",COUNTIFS('Recipe BOM'!$B:$B,A9,'Recipe BOM'!$D:$D,"<>",'Recipe BOM'!$L:$L,"<>OK")) | K9: =IF(A9="","",IF(I9=0,"No recipe",IF(J9>0,"Check recipe/items",IF(D9="","Enter selling price","OK"))))
A10: =IF(Products!A10="","",Products!A10) | B10: =IF(A10="","",Products!B10) | C10: =IF(A10="","",Products!C10) | D10: =IF(A10="","",Products!D10) | E10: =IF(A10="","",SUMIFS('Recipe BOM'!$K:$K,'Recipe BOM'!$B:$B,A10)) | F10: =IF(OR(A10="",D10="",E10=""),"",D10-E10) | G10: =IF(OR(A10="",D10="",E10=""),"",F10/D10) | H10: =IF(OR(A10="",D10="",E10=""),"",E10/D10) | I10: =IF(A10="","",COUNTIFS('Recipe BOM'!$B:$B,A10,'Recipe BOM'!$D:$D,"<>")) | J10: =IF(A10="","",COUNTIFS('Recipe BOM'!$B:$B,A10,'Recipe BOM'!$D:$D,"<>",'Recipe BOM'!$L:$L,"<>OK")) | K10: =IF(A10="","",IF(I10=0,"No recipe",IF(J10>0,"Check recipe/items",IF(D10="","Enter selling price","OK"))))
A11: =IF(Products!A11="","",Products!A11) | B11: =IF(A11="","",Products!B11) | C11: =IF(A11="","",Products!C11) | D11: =IF(A11="","",Products!D11) | E11: =IF(A11="","",SUMIFS('Recipe BOM'!$K:$K,'Recipe BOM'!$B:$B,A11)) | F11: =IF(OR(A11="",D11="",E11=""),"",D11-E11) | G11: =IF(OR(A11="",D11="",E11=""),"",F11/D11) | H11: =IF(OR(A11="",D11="",E11=""),"",E11/D11) | I11: =IF(A11="","",COUNTIFS('Recipe BOM'!$B:$B,A11,'Recipe BOM'!$D:$D,"<>")) | J11: =IF(A11="","",COUNTIFS('Recipe BOM'!$B:$B,A11,'Recipe BOM'!$D:$D,"<>",'Recipe BOM'!$L:$L,"<>OK")) | K11: =IF(A11="","",IF(I11=0,"No recipe",IF(J11>0,"Check recipe/items",IF(D11="","Enter selling price","OK"))))
A12: =IF(Products!A12="","",Products!A12) | B12: =IF(A12="","",Products!B12) | C12: =IF(A12="","",Products!C12) | D12: =IF(A12="","",Products!D12) | E12: =IF(A12="","",SUMIFS('Recipe BOM'!$K:$K,'Recipe BOM'!$B:$B,A12)) | F12: =IF(OR(A12="",D12="",E12=""),"",D12-E12) | G12: =IF(OR(A12="",D12="",E12=""),"",F12/D12) | H12: =IF(OR(A12="",D12="",E12=""),"",E12/D12) | I12: =IF(A12="","",COUNTIFS('Recipe BOM'!$B:$B,A12,'Recipe BOM'!$D:$D,"<>")) | J12: =IF(A12="","",COUNTIFS('Recipe BOM'!$B:$B,A12,'Recipe BOM'!$D:$D,"<>",'Recipe BOM'!$L:$L,"<>OK")) | K12: =IF(A12="","",IF(I12=0,"No recipe",IF(J12>0,"Check recipe/items",IF(D12="","Enter selling price","OK"))))
A13: =IF(Products!A13="","",Products!A13) | B13: =IF(A13="","",Products!B13) | C13: =IF(A13="","",Products!C13) | D13: =IF(A13="","",Products!D13) | E13: =IF(A13="","",SUMIFS('Recipe BOM'!$K:$K,'Recipe BOM'!$B:$B,A13)) | F13: =IF(OR(A13="",D13="",E13=""),"",D13-E13) | G13: =IF(OR(A13="",D13="",E13=""),"",F13/D13) | H13: =IF(OR(A13="",D13="",E13=""),"",E13/D13) | I13: =IF(A13="","",COUNTIFS('Recipe BOM'!$B:$B,A13,'Recipe BOM'!$D:$D,"<>")) | J13: =IF(A13="","",COUNTIFS('Recipe BOM'!$B:$B,A13,'Recipe BOM'!$D:$D,"<>",'Recipe BOM'!$L:$L,"<>OK")) | K13: =IF(A13="","",IF(I13=0,"No recipe",IF(J13>0,"Check recipe/items",IF(D13="","Enter selling price","OK"))))
... A201: =IF(Products!A201="","",Products!A201) | B201: =IF(A201="","",Products!B201) | C201: =IF(A201="","",Products!C201) | D201: =IF(A201="","",Products!D201) | E201: =IF(A201="","",SUMIFS('Recipe BOM'!$K:$K,'Recipe BOM'!$B:$B,A201)) | F201: =IF(OR(A201="",D201="",E201=""),"",D201-E201) | G201: =IF(OR(A201="",D201="",E201=""),"",F201/D201) | H201: =IF(OR(A201="",D201="",E201=""),"",E201/D201) | I201: =IF(A201="","",COUNTIFS('Recipe BOM'!$B:$B,A201,'Recipe BOM'!$D:$D,"<>")) | J201: =IF(A201="","",COUNTIFS('Recipe BOM'!$B:$B,A201,'Recipe BOM'!$D:$D,"<>",'Recipe BOM'!$L:$L,"<>OK")) | K201: =IF(A201="","",IF(I201=0,"No recipe",IF(J201>0,"Check recipe/items",IF(D201="","Enter selling price","OK"))))
